natus_command/__init__.py
natus_command/main.py
natus_command/prompts.py
natus_command-2025.12.21112934.dist-info/METADATA
natus_command-2025.12.21112934.dist-info/WHEEL
natus_command-2025.12.21112934.dist-info/top_level.txt
natus_command-2025.12.21112934.dist-info/RECORD
