Metadata-Version: 2.4
Name: natus-command
Version: 2025.12.21112934
Summary: A new package designed to interpret user descriptions of system maintenance, backup routines, and dotfile management tasks, and convert them into structured commands or step-by-step procedures. It tak
Author-email: natus-command <hi@eugene.plus>
License: MIT
Project-URL: Homepage, https://github.com/chigwell/natus-command
Requires-Python: >=3.9
Requires-Dist: langchain-llm7>=0.0.0
Requires-Dist: llmatch-messages>=0.0.0
Requires-Dist: langchain-core>=0.3.0
